LICENSE
README.rst
setup.py
atlasify/__init__.py
atlasify.egg-info/PKG-INFO
atlasify.egg-info/SOURCES.txt
atlasify.egg-info/dependency_links.txt
atlasify.egg-info/requires.txt
atlasify.egg-info/top_level.txt
atlasify/fonts/NimbusSans-Bold.ttf
atlasify/fonts/NimbusSans-BoldItalic.ttf
atlasify/fonts/NimbusSans-Italic.ttf
atlasify/fonts/NimbusSans-Regular.ttf
atlasify/tests/__init__.py
atlasify/tests/test_main.py