Metadata-Version: 2.1
Name: atlasify
Version: 0.8.0
Summary: Applies ATLAS style to matplotlib plots
Home-page: https://gitlab.cern.ch/fsauerbu/atlasify
Author: Frank Sauerburger
Author-email: f.sauerburger@cern.ch
License: AGPL-3.0
Platform: UNKNOWN
Classifier: Intended Audience :: Science/Research
Classifier: License :: OSI Approved :: GNU General Public License v2 (GPLv2)
Classifier: Operating System :: OS Independent
Classifier: Programming Language :: Python :: 3.7
Classifier: Programming Language :: Python :: 3.8
Classifier: Programming Language :: Python :: 3.9
Classifier: Programming Language :: Python :: 3.10
Classifier: Topic :: Scientific/Engineering :: Physics
License-File: LICENSE
